pyer/__init__.py
dgnpyer-1.0.5.dist-info/METADATA
dgnpyer-1.0.5.dist-info/WHEEL
dgnpyer-1.0.5.dist-info/top_level.txt
dgnpyer-1.0.5.dist-info/RECORD
