Metadata-Version: 2.4
Name: Dgnpyer
Version: 1.0.5
Summary: 一个包含字符转换、十进制转二进制和版本信息的Python库
Author: Gtl GuoTenglong
Author-email: vvvmcvvv@163.com
Classifier: Programming Language :: Python :: 3
Classifier: License :: OSI Approved :: MIT License
Classifier: Operating System :: OS Independent
Requires-Python: >=3.6
Dynamic: author
Dynamic: author-email
Dynamic: classifier
Dynamic: requires-python
Dynamic: summary
